maedeep/__init__.py
maedeep/_areafunction.py
maedeep/_config.py
maedeep/_contour.py
maedeep/_set.py
maedeep/_waveguide.py
maedeep/gmmtools.py
maedeep/signaltools.py
maedeep/data/data_vowels.h5
maedeep/dnn/__init__.py
maedeep/dnn/_forwardmapping.py
maedeep/dnn/_inversemapping.py
maedeep/dnn/costs.py
maedeep/dnn/dnntools.py
maedeep/dnn/optimizationtools.py
maedeep/dnn/models/acoustic_to_articulator.h5
maedeep/dnn/models/acoustic_to_articulatory_and_task.h5
maedeep/dnn/models/articulator_to_acoustic.h5
maedeep/dnn/models/articulator_to_acoustic_and_task.h5
maedeep/dnn/models/articulator_to_area.h5
maedeep/dnn/models/articulator_to_contour.h5
maedeep/dnn/models/articulator_to_task.h5
maedeep/dnn/models/contour_to_acoustic.h5
maedeep/dnn/models/contour_to_area.h5
maedeep/dnn/models/contour_to_articulatory.h5
maedeep/dnn/models/contour_to_task.h5
maedeep/dnn/models/task_to_acoustic.h5
maedeep/linear/__init__.py
maedeep/linear/_forwardmapping.py
maedeep/linear/modeltools.py
maedeep/linear/models/linear_model.h5
maedeep/parametric/__init__.py
maedeep/parametric/_forwardmapping.py
maedeep/parametric/_inversemapping.py
maedeep/parametric/modeltools.py
maedeep/parametric/optimtools.py
maedeep/parametric/models/model_spec.json
maedeep-0.1.1.dist-info/LICENSE.txt
maedeep-0.1.1.dist-info/METADATA
maedeep-0.1.1.dist-info/WHEEL
maedeep-0.1.1.dist-info/top_level.txt
maedeep-0.1.1.dist-info/RECORD
